pydantic_graph_interrupt/__init__.py
pydantic_graph_interrupt/graph.py
pydantic_graph_interrupt/nodes.py
pydantic_graph_interrupt-0.1.0.dist-info/METADATA
pydantic_graph_interrupt-0.1.0.dist-info/WHEEL
pydantic_graph_interrupt-0.1.0.dist-info/licenses/LICENSE
pydantic_graph_interrupt-0.1.0.dist-info/RECORD
