Metadata-Version: 2.4
Name: pydantic-graph-interrupt
Version: 0.1.0
Summary: Interrupt nodes for pydantic-graph
Project-URL: Homepage, https://github.com/vduseev/pydantic-graph-interrupt
Project-URL: Documentation, https://github.com/vduseev/pydantic-graph-interrupt
Project-URL: Repository, https://github.com/vduseev/pydantic-graph-interrupt
Project-URL: Issues, https://github.com/vduseev/pydantic-graph-interrupt/issues
Author-email: vduseev <vagiz@duseev.com>
Maintainer-email: vduseev <vagiz@duseev.com>
License-Expression: Apache-2.0
License-File: LICENSE
Keywords: graph,interrupt,pydantic,pydantic-graph
Classifier: Development Status :: 3 - Alpha
Classifier: Intended Audience :: Developers
Classifier: License :: OSI Approved :: Apache Software License
Classifier: Programming Language :: Python :: 3
Classifier: Programming Language :: Python :: 3.10
Classifier: Programming Language :: Python :: 3.11
Classifier: Programming Language :: Python :: 3.12
Classifier: Programming Language :: Python :: 3.13
Classifier: Programming Language :: Python :: 3.14
Classifier: Programming Language :: Python :: 3.15
Classifier: Topic :: Software Development :: Libraries
Classifier: Topic :: Software Development :: Libraries :: Application Frameworks
Classifier: Topic :: Software Development :: Libraries :: Python Modules
Requires-Python: >=3.10
Requires-Dist: pydantic-graph-persistence>=0.1.1
Requires-Dist: pydantic-graph>=1.0.0
